__init__.py
papers_dl.py
version.py
fetch/__init__.py
fetch/fetch.py
parse/__init__.py
parse/parse.py
providers/__init__.py
providers/arxiv.py
providers/scidb.py
providers/scihub.py
papers_dl-0.0.23.dist-info/LICENSE
papers_dl-0.0.23.dist-info/METADATA
papers_dl-0.0.23.dist-info/WHEEL
papers_dl-0.0.23.dist-info/entry_points.txt
papers_dl-0.0.23.dist-info/top_level.txt
papers_dl-0.0.23.dist-info/RECORD
